sparkai/__init__.py
test/__init__.py
test/test.py
sparkai-0.3.0.dist-info/LICENSE
sparkai-0.3.0.dist-info/METADATA
sparkai-0.3.0.dist-info/WHEEL
sparkai-0.3.0.dist-info/top_level.txt
sparkai-0.3.0.dist-info/RECORD
