Metadata-Version: 2.1
Name: sparkai
Version: 0.3.0
Summary: SparkAI official Python client library
Home-page: https://github.com/sparkai-corp/sparkai-python-client
Author: SparkAI
Author-email: support@spark.ai
Project-URL: Bug Tracker, https://github.com/sparkai-corp/sparkai-python-client/issues
Classifier: Programming Language :: Python :: 3
Classifier: License :: OSI Approved :: MIT License
Classifier: Operating System :: OS Independent
Requires-Python: >=3.4
License-File: LICENSE
